pyimgproxy/__init__.py
pyimgproxy/exceptions.py
pyimgproxy/image.py
pyimgproxy/imgproxy.py
pyimgproxy-0.4.dist-info/licenses/LICENSE
pyimgproxy-0.4.dist-info/METADATA
pyimgproxy-0.4.dist-info/WHEEL
pyimgproxy-0.4.dist-info/top_level.txt
pyimgproxy-0.4.dist-info/RECORD
