Metadata-Version: 2.4
Name: pyimgproxy
Version: 0.4
Summary: Python client for imgproxy
Maintainer-email: The Developer Society <studio@dev.ngo>
License-Expression: BSD-3-Clause
Project-URL: Homepage, https://github.com/developersociety/pyimgproxy
Classifier: Intended Audience :: Developers
Classifier: Operating System :: OS Independent
Classifier: Programming Language :: Python
Classifier: Programming Language :: Python :: 3
Classifier: Programming Language :: Python :: 3.10
Classifier: Programming Language :: Python :: 3.11
Classifier: Programming Language :: Python :: 3.12
Classifier: Programming Language :: Python :: 3.13
Classifier: Programming Language :: Python :: 3.14
Requires-Python: >=3.10
License-File: LICENSE
Dynamic: license-file
